ts_docs/__init__.py
ts_docs/build_docs.py
ts_docs/conf_docs.py
ts_docs/_static/timesintelli-logo.jpg
ts_docs/_static/timesintelli.jpg
ts_docs/_static/timesintelli_logo.jpg
ts_docs/_static/watermark.png
ts_docs/at_extensions/__init__.py
ts_docs/at_extensions/link_roles.py
ts_docs/latex_templates/preamble.tex
ts_docs/latex_templates/timesintelli.sty
ts_docs/latex_templates/titlepage.log
ts_docs/latex_templates/titlepage.tex
ts_docs-0.9.6.dist-info/METADATA
ts_docs-0.9.6.dist-info/WHEEL
ts_docs-0.9.6.dist-info/entry_points.txt
ts_docs-0.9.6.dist-info/top_level.txt
ts_docs-0.9.6.dist-info/RECORD
